LICENSE
MANIFEST.in
README.md
setup.cfg
setup.py
src/T3SF/T3SF.py
src/T3SF/__init__.py
src/T3SF/utils.py
src/T3SF.egg-info/PKG-INFO
src/T3SF.egg-info/SOURCES.txt
src/T3SF.egg-info/dependency_links.txt
src/T3SF.egg-info/requires.txt
src/T3SF.egg-info/top_level.txt
src/T3SF/discord/__init__.py
src/T3SF/discord/bot.py
src/T3SF/discord/discord.py
src/T3SF/gui/__init__.py
src/T3SF/gui/core.py
src/T3SF/gui/t3sf.sqlite3
src/T3SF/gui/static/imgs/icon.png
src/T3SF/gui/static/imgs/logo-dark.png
src/T3SF/gui/static/imgs/logo-light.png
src/T3SF/gui/static/js/bootstrap_toasts.js
src/T3SF/gui/static/js/copy.js
src/T3SF/gui/static/js/theme_switcher.js
src/T3SF/gui/static/js/vanilla-jsoneditor/CHANGELOG.md
src/T3SF/gui/static/js/vanilla-jsoneditor/LICENSE.md
src/T3SF/gui/static/js/vanilla-jsoneditor/README.md
src/T3SF/gui/static/js/vanilla-jsoneditor/SECURITY.md
src/T3SF/gui/static/js/vanilla-jsoneditor/index.d.ts
src/T3SF/gui/static/js/vanilla-jsoneditor/index.js
src/T3SF/gui/static/js/vanilla-jsoneditor/index.js.map
src/T3SF/gui/static/js/vanilla-jsoneditor/package.json
src/T3SF/gui/static/js/vanilla-jsoneditor/themes/jse-theme-dark.css
src/T3SF/gui/static/js/vanilla-jsoneditor/themes/jse-theme-default.css
src/T3SF/gui/templates/base.html
src/T3SF/gui/templates/env_creation.html
src/T3SF/gui/templates/index.html
src/T3SF/gui/templates/msel_playground.html
src/T3SF/logger/__init__.py
src/T3SF/logger/logger.py
src/T3SF/slack/__init__.py
src/T3SF/slack/bot.py
src/T3SF/slack/slack.py