Metadata-Version: 2.1
Name: T3SF
Version: 2.5.1
Summary: Technical Tabletop Exercises Simulation Framework
Home-page: https://github.com/Base4Security/T3SF
Author: BASE4 Security
Author-email: jlanfranconi@base4sec.com
Project-URL: Bug Tracker, https://github.com/Base4Security/T3SF/issues
Classifier: Programming Language :: Python :: 3
Classifier: License :: OSI Approved :: GNU General Public License v3 (GPLv3)
Classifier: Topic :: Software Development :: Libraries :: Application Frameworks
Classifier: Operating System :: OS Independent
Provides-Extra: Slack
Provides-Extra: Discord
License-File: LICENSE
